pubmed_extract/__init__.py
pubmed_extract/extraction.py
pubmed_extract/keywords.py
pubmed_extract/matcher.py
pubmed_extract/normalization.py
pubmed_extract/parse.py
pubmed_extract/test.py
pubmed_extract/utils.py
pubmed_extract-0.1.dist-info/LICENSE
pubmed_extract-0.1.dist-info/METADATA
pubmed_extract-0.1.dist-info/WHEEL
pubmed_extract-0.1.dist-info/top_level.txt
pubmed_extract-0.1.dist-info/RECORD
