Metadata-Version: 2.1
Name: pubmed-extract
Version: 0.1
Summary: Python Distribution Utilities
Home-page: https://skumarashutosh.github.io/
Author: Ashutosh Kumar
Author-email: akashutosh09@gmail.com
License-File: LICENSE
